[
  {
    "catalogID": "M31",
    "commonName": "Andromeda Galaxy",
    "primaryDesignation": "NGC 224",
    "catalogFamily": "messier",
    "alternateDesignations": ["M31", "Andromeda Galaxy"],
    "objectType": "galaxy",
    "constellation": "Andromeda",
    "rightAscensionHours": 0.712,
    "declinationDegrees": 41.269,
    "magnitude": 3.4,
    "angularSizeArcMinutes": 178.0,
    "surfaceBrightness": 13.5
  },
  {
    "catalogID": "M42",
    "commonName": "Orion Nebula",
    "primaryDesignation": "NGC 1976",
    "catalogFamily": "messier",
    "alternateDesignations": ["M42", "Great Orion Nebula"],
    "objectType": "emissionNebula",
    "constellation": "Orion",
    "rightAscensionHours": 5.591,
    "declinationDegrees": -5.45,
    "magnitude": 4.0,
    "angularSizeArcMinutes": 65.0,
    "surfaceBrightness": 11.0
  },
  {
    "catalogID": "M45",
    "commonName": "Pleiades",
    "primaryDesignation": "Melotte 22",
    "catalogFamily": "messier",
    "alternateDesignations": ["M45", "Seven Sisters"],
    "objectType": "openCluster",
    "constellation": "Taurus",
    "rightAscensionHours": 3.792,
    "declinationDegrees": 24.117,
    "magnitude": 1.6,
    "angularSizeArcMinutes": 110.0,
    "surfaceBrightness": 12.4
  },
  {
    "catalogID": "M13",
    "commonName": "Great Hercules Cluster",
    "primaryDesignation": "NGC 6205",
    "catalogFamily": "messier",
    "alternateDesignations": ["M13"],
    "objectType": "globularCluster",
    "constellation": "Hercules",
    "rightAscensionHours": 16.695,
    "declinationDegrees": 36.467,
    "magnitude": 5.8,
    "angularSizeArcMinutes": 20.0,
    "surfaceBrightness": 11.7
  },
  {
    "catalogID": "M27",
    "commonName": "Dumbbell Nebula",
    "primaryDesignation": "NGC 6853",
    "catalogFamily": "messier",
    "alternateDesignations": ["M27"],
    "objectType": "planetaryNebula",
    "constellation": "Vulpecula",
    "rightAscensionHours": 19.993,
    "declinationDegrees": 22.721,
    "magnitude": 7.5,
    "angularSizeArcMinutes": 8.0,
    "surfaceBrightness": 13.8
  },
  {
    "catalogID": "M57",
    "commonName": "Ring Nebula",
    "primaryDesignation": "NGC 6720",
    "catalogFamily": "messier",
    "alternateDesignations": ["M57"],
    "objectType": "planetaryNebula",
    "constellation": "Lyra",
    "rightAscensionHours": 18.893,
    "declinationDegrees": 33.03,
    "magnitude": 8.8,
    "angularSizeArcMinutes": 1.4,
    "surfaceBrightness": 9.0
  },
  {
    "catalogID": "M51",
    "commonName": "Whirlpool Galaxy",
    "primaryDesignation": "NGC 5194",
    "catalogFamily": "messier",
    "alternateDesignations": ["M51"],
    "objectType": "galaxy",
    "constellation": "Canes Venatici",
    "rightAscensionHours": 13.497,
    "declinationDegrees": 47.195,
    "magnitude": 8.4,
    "angularSizeArcMinutes": 11.2,
    "surfaceBrightness": 13.4
  },
  {
    "catalogID": "NGC 7000",
    "commonName": "North America Nebula",
    "primaryDesignation": "NGC 7000",
    "catalogFamily": "ngc",
    "alternateDesignations": ["North America Nebula", "C20"],
    "objectType": "emissionNebula",
    "constellation": "Cygnus",
    "rightAscensionHours": 20.973,
    "declinationDegrees": 44.53,
    "magnitude": 4.0,
    "angularSizeArcMinutes": 120.0,
    "surfaceBrightness": 15.0
  },
  {
    "catalogID": "NGC 869",
    "commonName": "Double Cluster",
    "primaryDesignation": "NGC 869/884",
    "catalogFamily": "ngc",
    "alternateDesignations": ["Double Cluster", "C14"],
    "objectType": "openCluster",
    "constellation": "Perseus",
    "rightAscensionHours": 2.33,
    "declinationDegrees": 57.13,
    "magnitude": 3.7,
    "angularSizeArcMinutes": 60.0,
    "surfaceBrightness": 12.8
  },
  {
    "catalogID": "NGC 6960",
    "commonName": "Western Veil Nebula",
    "primaryDesignation": "NGC 6960",
    "catalogFamily": "ngc",
    "alternateDesignations": ["Veil Nebula", "C33"],
    "objectType": "supernovaRemnant",
    "constellation": "Cygnus",
    "rightAscensionHours": 20.757,
    "declinationDegrees": 30.72,
    "magnitude": 7.0,
    "angularSizeArcMinutes": 180.0,
    "surfaceBrightness": 14.5
  },
  {
    "catalogID": "C14",
    "commonName": "Double Cluster",
    "primaryDesignation": "NGC 869 / NGC 884",
    "catalogFamily": "caldwell",
    "alternateDesignations": ["Caldwell 14", "NGC 869", "NGC 884"],
    "objectType": "openCluster",
    "constellation": "Perseus",
    "rightAscensionHours": 2.33,
    "declinationDegrees": 57.13,
    "magnitude": 3.7,
    "angularSizeArcMinutes": 60.0,
    "surfaceBrightness": 12.8
  },
  {
    "catalogID": "C20",
    "commonName": "North America Nebula",
    "primaryDesignation": "NGC 7000",
    "catalogFamily": "caldwell",
    "alternateDesignations": ["Caldwell 20", "NGC 7000"],
    "objectType": "emissionNebula",
    "constellation": "Cygnus",
    "rightAscensionHours": 20.973,
    "declinationDegrees": 44.53,
    "magnitude": 4.0,
    "angularSizeArcMinutes": 120.0,
    "surfaceBrightness": 15.0
  },
  {
    "catalogID": "IC 434",
    "commonName": "Horsehead Region",
    "primaryDesignation": "IC 434",
    "catalogFamily": "ic",
    "alternateDesignations": ["Horsehead Nebula", "Barnard 33"],
    "objectType": "darkNebula",
    "constellation": "Orion",
    "rightAscensionHours": 5.694,
    "declinationDegrees": -2.45,
    "magnitude": 7.3,
    "angularSizeArcMinutes": 60.0,
    "surfaceBrightness": 14.7
  },
  {
    "catalogID": "IC 1396",
    "commonName": "Elephant Trunk Region",
    "primaryDesignation": "IC 1396",
    "catalogFamily": "ic",
    "alternateDesignations": ["Elephant Trunk Nebula"],
    "objectType": "emissionNebula",
    "constellation": "Cepheus",
    "rightAscensionHours": 21.646,
    "declinationDegrees": 57.5,
    "magnitude": 5.0,
    "angularSizeArcMinutes": 170.0,
    "surfaceBrightness": 15.0
  },
  {
    "catalogID": "Sh2-155",
    "commonName": "Cave Nebula",
    "primaryDesignation": "Sh2-155",
    "catalogFamily": "sharpless2",
    "alternateDesignations": ["Sharpless 155", "Caldwell 9"],
    "objectType": "emissionNebula",
    "constellation": "Cepheus",
    "rightAscensionHours": 22.587,
    "declinationDegrees": 62.59,
    "magnitude": 7.7,
    "angularSizeArcMinutes": 50.0,
    "surfaceBrightness": 14.2
  },
  {
    "catalogID": "Sh2-240",
    "commonName": "Spaghetti Nebula",
    "primaryDesignation": "Sh2-240",
    "catalogFamily": "sharpless2",
    "alternateDesignations": ["Sharpless 240", "Simeis 147"],
    "objectType": "supernovaRemnant",
    "constellation": "Taurus",
    "rightAscensionHours": 5.66,
    "declinationDegrees": 27.3,
    "magnitude": 6.0,
    "angularSizeArcMinutes": 180.0,
    "surfaceBrightness": 15.0
  },
  {
    "catalogID": "LBN 438",
    "commonName": "Ghost Nebula",
    "primaryDesignation": "LBN 438",
    "catalogFamily": "lbn",
    "alternateDesignations": ["vdB 141", "Caldwell 4"],
    "objectType": "reflectionNebula",
    "constellation": "Cepheus",
    "rightAscensionHours": 0.194,
    "declinationDegrees": 67.15,
    "magnitude": 8.0,
    "angularSizeArcMinutes": 15.0,
    "surfaceBrightness": 14.0
  },
  {
    "catalogID": "LBN 487",
    "commonName": "Iris Region",
    "primaryDesignation": "LBN 487",
    "catalogFamily": "lbn",
    "alternateDesignations": ["Iris Nebula", "NGC 7023"],
    "objectType": "reflectionNebula",
    "constellation": "Cepheus",
    "rightAscensionHours": 21.013,
    "declinationDegrees": 68.17,
    "magnitude": 6.8,
    "angularSizeArcMinutes": 18.0,
    "surfaceBrightness": 13.5
  }
]
